alexandreleclercq_picsou/__init__.py
alexandreleclercq_picsou/picsou.py
alexandreleclercq_picsou-0.1.0.dist-info/METADATA
alexandreleclercq_picsou-0.1.0.dist-info/WHEEL
alexandreleclercq_picsou-0.1.0.dist-info/RECORD
