Metadata-Version: 2.1
Name: alexandreleclercq-picsou
Version: 0.1.0
Summary: 
Author: LeclercqAlexandre
Author-email: alexandre@famille-leclercq.fr
Requires-Python: ==3.10.9
Classifier: Programming Language :: Python :: 3
Requires-Dist: coverage (>=7.4.1,<8.0.0)
Requires-Dist: pillow (==10.1.0)
